gunsan_strength/__init__.py
gunsan_strength/core.py
gunsan_strength/plots.py
gunsan_strength-0.1.1.dist-info/LICENSE
gunsan_strength-0.1.1.dist-info/METADATA
gunsan_strength-0.1.1.dist-info/WHEEL
gunsan_strength-0.1.1.dist-info/top_level.txt
gunsan_strength-0.1.1.dist-info/RECORD
