Metadata-Version: 2.2
Name: gunsan_strength
Version: 0.1.1
Summary: GunSan Strength Index (GSI) – A proprietary leading and lagging indicator for measuring technical strength of a scrip.
Author: santosh3110
Author-email: santoshkumarguntupalli@gmail.com
Classifier: License :: OSI Approved :: Apache Software License
Classifier: Programming Language :: Python :: 3
Classifier: Operating System :: OS Independent
Requires-Python: >=3.7
License-File: LICENSE
Requires-Dist: pandas
Requires-Dist: numpy
Requires-Dist: vectorbt
Requires-Dist: pandas-ta
Requires-Dist: plotly
Dynamic: author
Dynamic: author-email
Dynamic: classifier
Dynamic: description
Dynamic: description-content-type
Dynamic: requires-dist
Dynamic: requires-python
Dynamic: summary
